Metadata-Version: 2.1
Name: pkg-FormulaBasedMaterials
Version: 0.1.0
Summary: A code for generating Formula-Based Materials into Voxel, STL files.
Home-page: https://github.com/MicDonald/FormulaBasedMaterials/archive/v0.1.0.tar.gz
Author: Michael, Yu-Chuan, Hsu
Author-email: mk60503mk60503@gmail.com
License: UNKNOWN
Platform: UNKNOWN
Classifier: Programming Language :: Python :: 3
Classifier: License :: OSI Approved :: MIT License
Classifier: Operating System :: OS Independent
Requires-Python: >=3.6
